pypix2svg/pypix2svg.py
pypix2svg-0.1.0.dist-info/COPYING
pypix2svg-0.1.0.dist-info/METADATA
pypix2svg-0.1.0.dist-info/WHEEL
pypix2svg-0.1.0.dist-info/entry_points.txt
pypix2svg-0.1.0.dist-info/top_level.txt
pypix2svg-0.1.0.dist-info/RECORD
