Metadata-Version: 2.1
Name: pypix2svg
Version: 0.1.0
Summary: Converts the pixels of a raster image to SVG for pixel-perfectness. Best for 8-bit or lower images.
Author-email: Nathanael Gentry <nathanael.gentrydb8@gmail.com>
License: GNU GENERAL PUBLIC LICENSE
Project-URL: homepage, https://github.com/npjg/pypix2svg
Project-URL: repository, https://github.com/npjg/pypix2svg
Keywords: reverse-engineering
Classifier: Programming Language :: Python :: 3
Classifier: License :: OSI Approved :: GNU General Public License v3 (GPLv3)
Classifier: Operating System :: OS Independent
Requires-Python: >=3.9
License-File: COPYING
Requires-Dist: Pillow >=9.2.0
